md4llm/__init__.py
md4llm/__main__.py
md4llm/server.py
md4llm-0.1.0.dist-info/METADATA
md4llm-0.1.0.dist-info/WHEEL
md4llm-0.1.0.dist-info/entry_points.txt
md4llm-0.1.0.dist-info/RECORD
